gecos/__init__.py
gecos/cli.py
gecos/colors.py
gecos/example_alignment.fasta
gecos/file.py
gecos/optimizer.py
gecos/space.npy
gecos/space.py
gecos-2.0.0.dist-info/entry_points.txt
gecos-2.0.0.dist-info/LICENSE.rst
gecos-2.0.0.dist-info/WHEEL
gecos-2.0.0.dist-info/METADATA
gecos-2.0.0.dist-info/RECORD
