Metadata-Version: 2.1
Name: gecos
Version: 2.0.0
Summary: Generated color schemes for sequence alignment visualizations
Home-page: https://gecos.biotite-python.org
License: BSD-3-Clause
Keywords: Bioinformatics,Computational biology,Data visualization
Author: Patrick Kunzmann
Author-email: patrick.kunzm@gmail.com
Requires-Python: >=3.6,<4.0
Classifier: Development Status :: 5 - Production/Stable
Classifier: Intended Audience :: Science/Research
Classifier: License :: OSI Approved :: BSD License
Classifier: Operating System :: OS Independent
Classifier: Programming Language :: Python :: 3
Classifier: Programming Language :: Python :: 3.10
Classifier: Programming Language :: Python :: 3.6
Classifier: Programming Language :: Python :: 3.7
Classifier: Programming Language :: Python :: 3.8
Classifier: Programming Language :: Python :: 3.9
Classifier: Topic :: Scientific/Engineering :: Bio-Informatics
Classifier: Topic :: Scientific/Engineering :: Visualization
Requires-Dist: biotite (>=0.21)
Requires-Dist: matplotlib (>=3.0,<4.0)
Requires-Dist: numpy (>=1.13,<2.0)
Requires-Dist: scikit-image (>=0.17)
Project-URL: Documentation, https://gecos.biotite-python.org
Project-URL: Repository, https://github.com/biotite-dev/gecos
